etl_history/__init__.py
etl_history/helper.py
etl_history-0.2.5.dist-info/METADATA
etl_history-0.2.5.dist-info/WHEEL
etl_history-0.2.5.dist-info/top_level.txt
etl_history-0.2.5.dist-info/RECORD
